codewise_lib/__init__.py
codewise_lib/crew.py
codewise_lib/cw_runner.py
codewise_lib/entradagit.py
codewise_lib/main.py
codewise_lib/config/agents.yaml
codewise_lib/config/tasks.yaml
scripts/__init__.py
scripts/codewise_review_win.py
scripts/help.py
scripts/install_hook.py
codewise-2.1.1.dist-info/METADATA
codewise-2.1.1.dist-info/WHEEL
codewise-2.1.1.dist-info/entry_points.txt
codewise-2.1.1.dist-info/top_level.txt
codewise-2.1.1.dist-info/RECORD
