Metadata-Version: 2.4
Name: codewise
Version: 2.1.1
Summary: análise de código e automação de PRs com CrewAI.
Author: BPC
Classifier: Programming Language :: Python :: 3
Classifier: Programming Language :: Python :: 3.11
Classifier: Operating System :: OS Independent
Classifier: Intended Audience :: Developers
Classifier: Topic :: Software Development :: Code Generators
Requires-Python: >=3.11
Requires-Dist: crewai
Requires-Dist: python-dotenv
Requires-Dist: pyyaml
Requires-Dist: google-generativeai
Requires-Dist: langchain-google-genai
Dynamic: author
Dynamic: classifier
Dynamic: description
Dynamic: description-content-type
Dynamic: requires-dist
Dynamic: requires-python
Dynamic: summary
